topsis_anerudh/__init__.py
topsis_anerudh/topsis_cli.py
Topsis_Anerudh_102203042-0.1.dist-info/LICENSE
Topsis_Anerudh_102203042-0.1.dist-info/METADATA
Topsis_Anerudh_102203042-0.1.dist-info/WHEEL
Topsis_Anerudh_102203042-0.1.dist-info/entry_points.txt
Topsis_Anerudh_102203042-0.1.dist-info/top_level.txt
Topsis_Anerudh_102203042-0.1.dist-info/RECORD
